kaztau/__init__.py
kaztau/__main__.py
kaztau/cli.py
kaztau/cliv2.py
kaztau/config.py
kaztau/database.py
kaztau/exceptions.py
kaztau/kaztau.py
kaztau/notifications.py
kaztau/telegram.py
kaztau/utils.py
kaztau/whatsapp.py
tests/__init__.py
tests/test_kaztau.py
tests/test_telegram.py
kaztau-0.2.0.dist-info/METADATA
kaztau-0.2.0.dist-info/WHEEL
kaztau-0.2.0.dist-info/entry_points.txt
kaztau-0.2.0.dist-info/top_level.txt
kaztau-0.2.0.dist-info/RECORD
