Metadata-Version: 2.1
Name: kaztau
Version: 0.2.0
Summary: Python app cli to send message
Home-page: https://github.com/btechpt/kaztau
Author: Boer Technology
Author-email: dev@btech.id
Classifier: Programming Language :: Python :: 3
Classifier: License :: OSI Approved :: MIT License
Classifier: Operating System :: OS Independent
Requires-Python: >=3.6
Requires-Dist: typer (==0.4.1)
Requires-Dist: pytest (==7.1.2)
Requires-Dist: Telethon (==1.24.0)
